{
  "status": "success",
  "type": "cellSetData",
  "data": {
    "epoch": 1,
    "cube": "NanoPivotCube",
    "axes": [
      {
        "id": 0,
        "hierarchies": [{ "dimension": "Scores", "hierarchy": "Team1Score" }],
        "positions": [
          [{ "namePath": ["AllMember"], "captionPath": ["AllMember"], "properties": { "DISPLAY_INFO": 65541 } }],
          [{ "namePath": ["AllMember", "0"], "captionPath": ["AllMember", "0"], "properties": { "DISPLAY_INFO": 0 } }],
          [
            {
              "namePath": ["AllMember", "1"],
              "captionPath": ["AllMember", "1"],
              "properties": { "DISPLAY_INFO": 131072 }
            }
          ],
          [
            {
              "namePath": ["AllMember", "2"],
              "captionPath": ["AllMember", "2"],
              "properties": { "DISPLAY_INFO": 131072 }
            }
          ],
          [
            {
              "namePath": ["AllMember", "3"],
              "captionPath": ["AllMember", "3"],
              "properties": { "DISPLAY_INFO": 131072 }
            }
          ],
          [
            {
              "namePath": ["AllMember", "5"],
              "captionPath": ["AllMember", "5"],
              "properties": { "DISPLAY_INFO": 131072 }
            }
          ]
        ]
      },
      {
        "id": 1,
        "hierarchies": [
          { "dimension": "Games", "hierarchy": "Games" },
          { "dimension": "Date Time", "hierarchy": "Date Time" }
        ],
        "positions": [
          [
            {
              "namePath": ["AllMember", "Argentina", "Croatia"],
              "captionPath": ["AllMember", "Argentina", "Croatia"],
              "properties": { "DISPLAY_INFO": 0 }
            },
            {
              "namePath": ["AllMember", "2018-06-21", "21:00"],
              "captionPath": ["AllMember", "2018-06-21", "21:00"],
              "properties": { "DISPLAY_INFO": 0 }
            }
          ],
          [
            {
              "namePath": ["AllMember", "Argentina", "Iceland"],
              "captionPath": ["AllMember", "Argentina", "Iceland"],
              "properties": { "DISPLAY_INFO": 131072 }
            },
            {
              "namePath": ["AllMember", "2018-06-16", "16:00"],
              "captionPath": ["AllMember", "2018-06-16", "16:00"],
              "properties": { "DISPLAY_INFO": 0 }
            }
          ],
          [
            {
              "namePath": ["AllMember", "Australia", "Peru"],
              "captionPath": ["AllMember", "Australia", "Peru"],
              "properties": { "DISPLAY_INFO": 0 }
            },
            {
              "namePath": ["AllMember", "2018-06-26", "17:00"],
              "captionPath": ["AllMember", "2018-06-26", "17:00"],
              "properties": { "DISPLAY_INFO": 0 }
            }
          ],
          [
            {
              "namePath": ["AllMember", "Belgium", "Panama"],
              "captionPath": ["AllMember", "Belgium", "Panama"],
              "properties": { "DISPLAY_INFO": 0 }
            },
            {
              "namePath": ["AllMember", "2018-06-18", "18:00"],
              "captionPath": ["AllMember", "2018-06-18", "18:00"],
              "properties": { "DISPLAY_INFO": 0 }
            }
          ],
          [
            {
              "namePath": ["AllMember", "Belgium", "Tunisia"],
              "captionPath": ["AllMember", "Belgium", "Tunisia"],
              "properties": { "DISPLAY_INFO": 131072 }
            },
            {
              "namePath": ["AllMember", "2018-06-23", "15:00"],
              "captionPath": ["AllMember", "2018-06-23", "15:00"],
              "properties": { "DISPLAY_INFO": 0 }
            }
          ],
          [
            {
              "namePath": ["AllMember", "Brazil", "Costa Rica"],
              "captionPath": ["AllMember", "Brazil", "Costa Rica"],
              "properties": { "DISPLAY_INFO": 0 }
            },
            {
              "namePath": ["AllMember", "2018-06-22", "15:00"],
              "captionPath": ["AllMember", "2018-06-22", "15:00"],
              "properties": { "DISPLAY_INFO": 0 }
            }
          ],
          [
            {
              "namePath": ["AllMember", "Brazil", "Switzerland"],
              "captionPath": ["AllMember", "Brazil", "Switzerland"],
              "properties": { "DISPLAY_INFO": 131072 }
            },
            {
              "namePath": ["AllMember", "2018-06-17", "21:00"],
              "captionPath": ["AllMember", "2018-06-17", "21:00"],
              "properties": { "DISPLAY_INFO": 0 }
            }
          ],
          [
            {
              "namePath": ["AllMember", "Colombia", "Japan"],
              "captionPath": ["AllMember", "Colombia", "Japan"],
              "properties": { "DISPLAY_INFO": 0 }
            },
            {
              "namePath": ["AllMember", "2018-06-19", "15:00"],
              "captionPath": ["AllMember", "2018-06-19", "15:00"],
              "properties": { "DISPLAY_INFO": 0 }
            }
          ],
          [
            {
              "namePath": ["AllMember", "Costa Rica"],
              "captionPath": ["AllMember", "Costa Rica"],
              "properties": { "DISPLAY_INFO": 1 }
            },
            {
              "namePath": ["AllMember", "2018-06-17", "16:00"],
              "captionPath": ["AllMember", "2018-06-17", "16:00"],
              "properties": { "DISPLAY_INFO": 0 }
            }
          ],
          [
            {
              "namePath": ["AllMember", "Croatia"],
              "captionPath": ["AllMember", "Croatia"],
              "properties": { "DISPLAY_INFO": 131073 }
            },
            {
              "namePath": ["AllMember", "2018-06-16", "21:00"],
              "captionPath": ["AllMember", "2018-06-16", "21:00"],
              "properties": { "DISPLAY_INFO": 0 }
            }
          ],
          [
            {
              "namePath": ["AllMember", "Denmark", "Australia"],
              "captionPath": ["AllMember", "Denmark", "Australia"],
              "properties": { "DISPLAY_INFO": 0 }
            },
            {
              "namePath": ["AllMember", "2018-06-21", "16:00"],
              "captionPath": ["AllMember", "2018-06-21", "16:00"],
              "properties": { "DISPLAY_INFO": 0 }
            }
          ],
          [
            {
              "namePath": ["AllMember", "Denmark", "France"],
              "captionPath": ["AllMember", "Denmark", "France"],
              "properties": { "DISPLAY_INFO": 131072 }
            },
            {
              "namePath": ["AllMember", "2018-06-26", "17:00"],
              "captionPath": ["AllMember", "2018-06-26", "17:00"],
              "properties": { "DISPLAY_INFO": 0 }
            }
          ],
          [
            {
              "namePath": ["AllMember", "Egypt", "Uruguay"],
              "captionPath": ["AllMember", "Egypt", "Uruguay"],
              "properties": { "DISPLAY_INFO": 0 }
            },
            {
              "namePath": ["AllMember", "2018-06-15", "17:00"],
              "captionPath": ["AllMember", "2018-06-15", "17:00"],
              "properties": { "DISPLAY_INFO": 0 }
            }
          ],
          [
            {
              "namePath": ["AllMember", "England"],
              "captionPath": ["AllMember", "England"],
              "properties": { "DISPLAY_INFO": 2 }
            },
            {
              "namePath": ["AllMember", "2018-06-24", "15:00"],
              "captionPath": ["AllMember", "2018-06-24", "15:00"],
              "properties": { "DISPLAY_INFO": 0 }
            }
          ],
          [
            {
              "namePath": ["AllMember", "England"],
              "captionPath": ["AllMember", "England"],
              "properties": { "DISPLAY_INFO": 131074 }
            },
            {
              "namePath": ["AllMember", "2018-06-28", "20:00"],
              "captionPath": ["AllMember", "2018-06-28", "20:00"],
              "properties": { "DISPLAY_INFO": 0 }
            }
          ],
          [
            {
              "namePath": ["AllMember", "France", "Australia"],
              "captionPath": ["AllMember", "France", "Australia"],
              "properties": { "DISPLAY_INFO": 0 }
            },
            {
              "namePath": ["AllMember", "2018-06-16", "13:00"],
              "captionPath": ["AllMember", "2018-06-16", "13:00"],
              "properties": { "DISPLAY_INFO": 0 }
            }
          ],
          [
            {
              "namePath": ["AllMember", "France", "Peru"],
              "captionPath": ["AllMember", "France", "Peru"],
              "properties": { "DISPLAY_INFO": 131072 }
            },
            {
              "namePath": ["AllMember", "2018-06-21", "20:00"],
              "captionPath": ["AllMember", "2018-06-21", "20:00"],
              "properties": { "DISPLAY_INFO": 0 }
            }
          ],
          [
            {
              "namePath": ["AllMember", "Germany", "Mexico"],
              "captionPath": ["AllMember", "Germany", "Mexico"],
              "properties": { "DISPLAY_INFO": 0 }
            },
            {
              "namePath": ["AllMember", "2018-06-17", "18:00"],
              "captionPath": ["AllMember", "2018-06-17", "18:00"],
              "properties": { "DISPLAY_INFO": 0 }
            }
          ],
          [
            {
              "namePath": ["AllMember", "Germany", "Sweden"],
              "captionPath": ["AllMember", "Germany", "Sweden"],
              "properties": { "DISPLAY_INFO": 131072 }
            },
            {
              "namePath": ["AllMember", "2018-06-23", "21:00"],
              "captionPath": ["AllMember", "2018-06-23", "21:00"],
              "properties": { "DISPLAY_INFO": 0 }
            }
          ],
          [
            {
              "namePath": ["AllMember", "Iceland"],
              "captionPath": ["AllMember", "Iceland"],
              "properties": { "DISPLAY_INFO": 1 }
            },
            {
              "namePath": ["AllMember", "2018-06-26", "21:00"],
              "captionPath": ["AllMember", "2018-06-26", "21:00"],
              "properties": { "DISPLAY_INFO": 0 }
            }
          ],
          [
            {
              "namePath": ["AllMember", "Iran"],
              "captionPath": ["AllMember", "Iran"],
              "properties": { "DISPLAY_INFO": 131074 }
            },
            {
              "namePath": ["AllMember", "2018-06-20", "21:00"],
              "captionPath": ["AllMember", "2018-06-20", "21:00"],
              "properties": { "DISPLAY_INFO": 0 }
            }
          ],
          [
            {
              "namePath": ["AllMember", "Iran"],
              "captionPath": ["AllMember", "Iran"],
              "properties": { "DISPLAY_INFO": 131074 }
            },
            {
              "namePath": ["AllMember", "2018-06-25", "21:00"],
              "captionPath": ["AllMember", "2018-06-25", "21:00"],
              "properties": { "DISPLAY_INFO": 0 }
            }
          ],
          [
            {
              "namePath": ["AllMember", "Japan"],
              "captionPath": ["AllMember", "Japan"],
              "properties": { "DISPLAY_INFO": 131074 }
            },
            {
              "namePath": ["AllMember", "2018-06-24", "20:00"],
              "captionPath": ["AllMember", "2018-06-24", "20:00"],
              "properties": { "DISPLAY_INFO": 0 }
            }
          ],
          [
            {
              "namePath": ["AllMember", "Japan"],
              "captionPath": ["AllMember", "Japan"],
              "properties": { "DISPLAY_INFO": 131074 }
            },
            {
              "namePath": ["AllMember", "2018-06-28", "17:00"],
              "captionPath": ["AllMember", "2018-06-28", "17:00"],
              "properties": { "DISPLAY_INFO": 0 }
            }
          ],
          [
            {
              "namePath": ["AllMember", "Mexico"],
              "captionPath": ["AllMember", "Mexico"],
              "properties": { "DISPLAY_INFO": 131073 }
            },
            {
              "namePath": ["AllMember", "2018-06-27", "19:00"],
              "captionPath": ["AllMember", "2018-06-27", "19:00"],
              "properties": { "DISPLAY_INFO": 0 }
            }
          ],
          [
            {
              "namePath": ["AllMember", "Morocco"],
              "captionPath": ["AllMember", "Morocco"],
              "properties": { "DISPLAY_INFO": 131073 }
            },
            {
              "namePath": ["AllMember", "2018-06-15", "18:00"],
              "captionPath": ["AllMember", "2018-06-15", "18:00"],
              "properties": { "DISPLAY_INFO": 0 }
            }
          ],
          [
            {
              "namePath": ["AllMember", "Nigeria"],
              "captionPath": ["AllMember", "Nigeria"],
              "properties": { "DISPLAY_INFO": 131074 }
            },
            {
              "namePath": ["AllMember", "2018-06-22", "18:00"],
              "captionPath": ["AllMember", "2018-06-22", "18:00"],
              "properties": { "DISPLAY_INFO": 0 }
            }
          ],
          [
            {
              "namePath": ["AllMember", "Nigeria"],
              "captionPath": ["AllMember", "Nigeria"],
              "properties": { "DISPLAY_INFO": 131074 }
            },
            {
              "namePath": ["AllMember", "2018-06-26", "21:00"],
              "captionPath": ["AllMember", "2018-06-26", "21:00"],
              "properties": { "DISPLAY_INFO": 0 }
            }
          ],
          [
            {
              "namePath": ["AllMember", "Panama"],
              "captionPath": ["AllMember", "Panama"],
              "properties": { "DISPLAY_INFO": 131073 }
            },
            {
              "namePath": ["AllMember", "2018-06-28", "21:00"],
              "captionPath": ["AllMember", "2018-06-28", "21:00"],
              "properties": { "DISPLAY_INFO": 0 }
            }
          ],
          [
            {
              "namePath": ["AllMember", "Peru"],
              "captionPath": ["AllMember", "Peru"],
              "properties": { "DISPLAY_INFO": 131073 }
            },
            {
              "namePath": ["AllMember", "2018-06-16", "19:00"],
              "captionPath": ["AllMember", "2018-06-16", "19:00"],
              "properties": { "DISPLAY_INFO": 0 }
            }
          ],
          [
            {
              "namePath": ["AllMember", "Poland"],
              "captionPath": ["AllMember", "Poland"],
              "properties": { "DISPLAY_INFO": 131074 }
            },
            {
              "namePath": ["AllMember", "2018-06-19", "18:00"],
              "captionPath": ["AllMember", "2018-06-19", "18:00"],
              "properties": { "DISPLAY_INFO": 0 }
            }
          ],
          [
            {
              "namePath": ["AllMember", "Poland"],
              "captionPath": ["AllMember", "Poland"],
              "properties": { "DISPLAY_INFO": 131074 }
            },
            {
              "namePath": ["AllMember", "2018-06-24", "21:00"],
              "captionPath": ["AllMember", "2018-06-24", "21:00"],
              "properties": { "DISPLAY_INFO": 0 }
            }
          ],
          [
            {
              "namePath": ["AllMember", "Portugal"],
              "captionPath": ["AllMember", "Portugal"],
              "properties": { "DISPLAY_INFO": 131074 }
            },
            {
              "namePath": ["AllMember", "2018-06-15", "21:00"],
              "captionPath": ["AllMember", "2018-06-15", "21:00"],
              "properties": { "DISPLAY_INFO": 0 }
            }
          ],
          [
            {
              "namePath": ["AllMember", "Portugal"],
              "captionPath": ["AllMember", "Portugal"],
              "properties": { "DISPLAY_INFO": 131074 }
            },
            {
              "namePath": ["AllMember", "2018-06-20", "15:00"],
              "captionPath": ["AllMember", "2018-06-20", "15:00"],
              "properties": { "DISPLAY_INFO": 0 }
            }
          ],
          [
            {
              "namePath": ["AllMember", "Russia"],
              "captionPath": ["AllMember", "Russia"],
              "properties": { "DISPLAY_INFO": 131074 }
            },
            {
              "namePath": ["AllMember", "2018-06-14", "18:00"],
              "captionPath": ["AllMember", "2018-06-14", "18:00"],
              "properties": { "DISPLAY_INFO": 0 }
            }
          ],
          [
            {
              "namePath": ["AllMember", "Russia"],
              "captionPath": ["AllMember", "Russia"],
              "properties": { "DISPLAY_INFO": 131074 }
            },
            {
              "namePath": ["AllMember", "2018-06-19", "21:00"],
              "captionPath": ["AllMember", "2018-06-19", "21:00"],
              "properties": { "DISPLAY_INFO": 0 }
            }
          ],
          [
            {
              "namePath": ["AllMember", "Saudi Arabia"],
              "captionPath": ["AllMember", "Saudi Arabia"],
              "properties": { "DISPLAY_INFO": 131073 }
            },
            {
              "namePath": ["AllMember", "2018-06-25", "17:00"],
              "captionPath": ["AllMember", "2018-06-25", "17:00"],
              "properties": { "DISPLAY_INFO": 0 }
            }
          ],
          [
            {
              "namePath": ["AllMember", "Senegal"],
              "captionPath": ["AllMember", "Senegal"],
              "properties": { "DISPLAY_INFO": 131073 }
            },
            {
              "namePath": ["AllMember", "2018-06-28", "18:00"],
              "captionPath": ["AllMember", "2018-06-28", "18:00"],
              "properties": { "DISPLAY_INFO": 0 }
            }
          ],
          [
            {
              "namePath": ["AllMember", "Serbia"],
              "captionPath": ["AllMember", "Serbia"],
              "properties": { "DISPLAY_INFO": 131074 }
            },
            {
              "namePath": ["AllMember", "2018-06-22", "20:00"],
              "captionPath": ["AllMember", "2018-06-22", "20:00"],
              "properties": { "DISPLAY_INFO": 0 }
            }
          ],
          [
            {
              "namePath": ["AllMember", "Serbia"],
              "captionPath": ["AllMember", "Serbia"],
              "properties": { "DISPLAY_INFO": 131074 }
            },
            {
              "namePath": ["AllMember", "2018-06-27", "21:00"],
              "captionPath": ["AllMember", "2018-06-27", "21:00"],
              "properties": { "DISPLAY_INFO": 0 }
            }
          ],
          [
            {
              "namePath": ["AllMember", "South Korea"],
              "captionPath": ["AllMember", "South Korea"],
              "properties": { "DISPLAY_INFO": 131074 }
            },
            {
              "namePath": ["AllMember", "2018-06-23", "18:00"],
              "captionPath": ["AllMember", "2018-06-23", "18:00"],
              "properties": { "DISPLAY_INFO": 0 }
            }
          ],
          [
            {
              "namePath": ["AllMember", "South Korea"],
              "captionPath": ["AllMember", "South Korea"],
              "properties": { "DISPLAY_INFO": 131074 }
            },
            {
              "namePath": ["AllMember", "2018-06-27", "17:00"],
              "captionPath": ["AllMember", "2018-06-27", "17:00"],
              "properties": { "DISPLAY_INFO": 0 }
            }
          ],
          [
            {
              "namePath": ["AllMember", "Spain"],
              "captionPath": ["AllMember", "Spain"],
              "properties": { "DISPLAY_INFO": 131073 }
            },
            {
              "namePath": ["AllMember", "2018-06-25", "20:00"],
              "captionPath": ["AllMember", "2018-06-25", "20:00"],
              "properties": { "DISPLAY_INFO": 0 }
            }
          ],
          [
            {
              "namePath": ["AllMember", "Sweden"],
              "captionPath": ["AllMember", "Sweden"],
              "properties": { "DISPLAY_INFO": 131073 }
            },
            {
              "namePath": ["AllMember", "2018-06-18", "15:00"],
              "captionPath": ["AllMember", "2018-06-18", "15:00"],
              "properties": { "DISPLAY_INFO": 0 }
            }
          ],
          [
            {
              "namePath": ["AllMember", "Switzerland"],
              "captionPath": ["AllMember", "Switzerland"],
              "properties": { "DISPLAY_INFO": 131073 }
            },
            {
              "namePath": ["AllMember", "2018-06-27", "21:00"],
              "captionPath": ["AllMember", "2018-06-27", "21:00"],
              "properties": { "DISPLAY_INFO": 0 }
            }
          ],
          [
            {
              "namePath": ["AllMember", "Tunisia"],
              "captionPath": ["AllMember", "Tunisia"],
              "properties": { "DISPLAY_INFO": 131073 }
            },
            {
              "namePath": ["AllMember", "2018-06-18", "21:00"],
              "captionPath": ["AllMember", "2018-06-18", "21:00"],
              "properties": { "DISPLAY_INFO": 0 }
            }
          ],
          [
            {
              "namePath": ["AllMember", "Uruguay"],
              "captionPath": ["AllMember", "Uruguay"],
              "properties": { "DISPLAY_INFO": 131074 }
            },
            {
              "namePath": ["AllMember", "2018-06-20", "18:00"],
              "captionPath": ["AllMember", "2018-06-20", "18:00"],
              "properties": { "DISPLAY_INFO": 0 }
            }
          ],
          [
            {
              "namePath": ["AllMember", "Uruguay"],
              "captionPath": ["AllMember", "Uruguay"],
              "properties": { "DISPLAY_INFO": 131074 }
            },
            {
              "namePath": ["AllMember", "2018-06-25", "18:00"],
              "captionPath": ["AllMember", "2018-06-25", "18:00"],
              "properties": { "DISPLAY_INFO": 0 }
            }
          ]
        ]
      },
      {
        "id": -1,
        "hierarchies": [{ "dimension": "Measures", "hierarchy": "Measures" }],
        "positions": [
          [{ "namePath": ["Total scores"], "captionPath": ["Total scores"], "properties": { "DISPLAY_INFO": 0 } }]
        ]
      }
    ],
    "cells": [
      {
        "ordinal": 0,
        "value": 0,
        "formattedValue": "0",
        "properties": { "FORE_COLOR": null, "FONT_FLAGS": 0, "BACK_COLOR": null }
      },
      {
        "ordinal": 1,
        "value": 0,
        "formattedValue": "0",
        "properties": { "FORE_COLOR": null, "FONT_FLAGS": 0, "BACK_COLOR": null }
      },
      {
        "ordinal": 6,
        "value": 2,
        "formattedValue": "2",
        "properties": { "FORE_COLOR": null, "FONT_FLAGS": 0, "BACK_COLOR": null }
      },
      {
        "ordinal": 8,
        "value": 2,
        "formattedValue": "2",
        "properties": { "FORE_COLOR": null, "FONT_FLAGS": 0, "BACK_COLOR": null }
      },
      {
        "ordinal": 12,
        "value": 0,
        "formattedValue": "0",
        "properties": { "FORE_COLOR": null, "FONT_FLAGS": 0, "BACK_COLOR": null }
      },
      {
        "ordinal": 13,
        "value": 0,
        "formattedValue": "0",
        "properties": { "FORE_COLOR": null, "FONT_FLAGS": 0, "BACK_COLOR": null }
      },
      {
        "ordinal": 18,
        "value": 3,
        "formattedValue": "3",
        "properties": { "FORE_COLOR": null, "FONT_FLAGS": 0, "BACK_COLOR": null }
      },
      {
        "ordinal": 22,
        "value": 3,
        "formattedValue": "3",
        "properties": { "FORE_COLOR": null, "FONT_FLAGS": 0, "BACK_COLOR": null }
      },
      {
        "ordinal": 24,
        "value": 0,
        "formattedValue": "0",
        "properties": { "FORE_COLOR": null, "FONT_FLAGS": 0, "BACK_COLOR": null }
      },
      {
        "ordinal": 25,
        "value": 0,
        "formattedValue": "0",
        "properties": { "FORE_COLOR": null, "FONT_FLAGS": 0, "BACK_COLOR": null }
      },
      {
        "ordinal": 30,
        "value": 0,
        "formattedValue": "0",
        "properties": { "FORE_COLOR": null, "FONT_FLAGS": 0, "BACK_COLOR": null }
      },
      {
        "ordinal": 31,
        "value": 0,
        "formattedValue": "0",
        "properties": { "FORE_COLOR": null, "FONT_FLAGS": 0, "BACK_COLOR": null }
      },
      {
        "ordinal": 36,
        "value": 2,
        "formattedValue": "2",
        "properties": { "FORE_COLOR": null, "FONT_FLAGS": 0, "BACK_COLOR": null }
      },
      {
        "ordinal": 38,
        "value": 2,
        "formattedValue": "2",
        "properties": { "FORE_COLOR": null, "FONT_FLAGS": 0, "BACK_COLOR": null }
      },
      {
        "ordinal": 42,
        "value": 3,
        "formattedValue": "3",
        "properties": { "FORE_COLOR": null, "FONT_FLAGS": 0, "BACK_COLOR": null }
      },
      {
        "ordinal": 44,
        "value": 3,
        "formattedValue": "3",
        "properties": { "FORE_COLOR": null, "FONT_FLAGS": 0, "BACK_COLOR": null }
      },
      {
        "ordinal": 48,
        "value": 1,
        "formattedValue": "1",
        "properties": { "FORE_COLOR": null, "FONT_FLAGS": 0, "BACK_COLOR": null }
      },
      {
        "ordinal": 49,
        "value": 1,
        "formattedValue": "1",
        "properties": { "FORE_COLOR": null, "FONT_FLAGS": 0, "BACK_COLOR": null }
      },
      {
        "ordinal": 54,
        "value": 2,
        "formattedValue": "2",
        "properties": { "FORE_COLOR": null, "FONT_FLAGS": 0, "BACK_COLOR": null }
      },
      {
        "ordinal": 57,
        "value": 2,
        "formattedValue": "2",
        "properties": { "FORE_COLOR": null, "FONT_FLAGS": 0, "BACK_COLOR": null }
      },
      {
        "ordinal": 60,
        "value": 0,
        "formattedValue": "0",
        "properties": { "FORE_COLOR": null, "FONT_FLAGS": 0, "BACK_COLOR": null }
      },
      {
        "ordinal": 61,
        "value": 0,
        "formattedValue": "0",
        "properties": { "FORE_COLOR": null, "FONT_FLAGS": 0, "BACK_COLOR": null }
      },
      {
        "ordinal": 66,
        "value": 0,
        "formattedValue": "0",
        "properties": { "FORE_COLOR": null, "FONT_FLAGS": 0, "BACK_COLOR": null }
      },
      {
        "ordinal": 67,
        "value": 0,
        "formattedValue": "0",
        "properties": { "FORE_COLOR": null, "FONT_FLAGS": 0, "BACK_COLOR": null }
      },
      {
        "ordinal": 72,
        "value": 1,
        "formattedValue": "1",
        "properties": { "FORE_COLOR": null, "FONT_FLAGS": 0, "BACK_COLOR": null }
      },
      {
        "ordinal": 73,
        "value": 1,
        "formattedValue": "1",
        "properties": { "FORE_COLOR": null, "FONT_FLAGS": 0, "BACK_COLOR": null }
      },
      {
        "ordinal": 78,
        "value": 0,
        "formattedValue": "0",
        "properties": { "FORE_COLOR": null, "FONT_FLAGS": 0, "BACK_COLOR": null }
      },
      {
        "ordinal": 79,
        "value": 0,
        "formattedValue": "0",
        "properties": { "FORE_COLOR": null, "FONT_FLAGS": 0, "BACK_COLOR": null }
      },
      {
        "ordinal": 84,
        "value": 0,
        "formattedValue": "0",
        "properties": { "FORE_COLOR": null, "FONT_FLAGS": 0, "BACK_COLOR": null }
      },
      {
        "ordinal": 85,
        "value": 0,
        "formattedValue": "0",
        "properties": { "FORE_COLOR": null, "FONT_FLAGS": 0, "BACK_COLOR": null }
      },
      {
        "ordinal": 90,
        "value": 3,
        "formattedValue": "3",
        "properties": { "FORE_COLOR": null, "FONT_FLAGS": 0, "BACK_COLOR": null }
      },
      {
        "ordinal": 93,
        "value": 3,
        "formattedValue": "3",
        "properties": { "FORE_COLOR": null, "FONT_FLAGS": 0, "BACK_COLOR": null }
      },
      {
        "ordinal": 96,
        "value": 0,
        "formattedValue": "0",
        "properties": { "FORE_COLOR": null, "FONT_FLAGS": 0, "BACK_COLOR": null }
      },
      {
        "ordinal": 97,
        "value": 0,
        "formattedValue": "0",
        "properties": { "FORE_COLOR": null, "FONT_FLAGS": 0, "BACK_COLOR": null }
      },
      {
        "ordinal": 102,
        "value": 1,
        "formattedValue": "1",
        "properties": { "FORE_COLOR": null, "FONT_FLAGS": 0, "BACK_COLOR": null }
      },
      {
        "ordinal": 103,
        "value": 1,
        "formattedValue": "1",
        "properties": { "FORE_COLOR": null, "FONT_FLAGS": 0, "BACK_COLOR": null }
      },
      {
        "ordinal": 108,
        "value": 0,
        "formattedValue": "0",
        "properties": { "FORE_COLOR": null, "FONT_FLAGS": 0, "BACK_COLOR": null }
      },
      {
        "ordinal": 109,
        "value": 0,
        "formattedValue": "0",
        "properties": { "FORE_COLOR": null, "FONT_FLAGS": 0, "BACK_COLOR": null }
      },
      {
        "ordinal": 114,
        "value": 0,
        "formattedValue": "0",
        "properties": { "FORE_COLOR": null, "FONT_FLAGS": 0, "BACK_COLOR": null }
      },
      {
        "ordinal": 115,
        "value": 0,
        "formattedValue": "0",
        "properties": { "FORE_COLOR": null, "FONT_FLAGS": 0, "BACK_COLOR": null }
      },
      {
        "ordinal": 120,
        "value": 0,
        "formattedValue": "0",
        "properties": { "FORE_COLOR": null, "FONT_FLAGS": 0, "BACK_COLOR": null }
      },
      {
        "ordinal": 121,
        "value": 0,
        "formattedValue": "0",
        "properties": { "FORE_COLOR": null, "FONT_FLAGS": 0, "BACK_COLOR": null }
      },
      {
        "ordinal": 126,
        "value": 0,
        "formattedValue": "0",
        "properties": { "FORE_COLOR": null, "FONT_FLAGS": 0, "BACK_COLOR": null }
      },
      {
        "ordinal": 127,
        "value": 0,
        "formattedValue": "0",
        "properties": { "FORE_COLOR": null, "FONT_FLAGS": 0, "BACK_COLOR": null }
      },
      {
        "ordinal": 132,
        "value": 0,
        "formattedValue": "0",
        "properties": { "FORE_COLOR": null, "FONT_FLAGS": 0, "BACK_COLOR": null }
      },
      {
        "ordinal": 133,
        "value": 0,
        "formattedValue": "0",
        "properties": { "FORE_COLOR": null, "FONT_FLAGS": 0, "BACK_COLOR": null }
      },
      {
        "ordinal": 138,
        "value": 0,
        "formattedValue": "0",
        "properties": { "FORE_COLOR": null, "FONT_FLAGS": 0, "BACK_COLOR": null }
      },
      {
        "ordinal": 139,
        "value": 0,
        "formattedValue": "0",
        "properties": { "FORE_COLOR": null, "FONT_FLAGS": 0, "BACK_COLOR": null }
      },
      {
        "ordinal": 144,
        "value": 0,
        "formattedValue": "0",
        "properties": { "FORE_COLOR": null, "FONT_FLAGS": 0, "BACK_COLOR": null }
      },
      {
        "ordinal": 145,
        "value": 0,
        "formattedValue": "0",
        "properties": { "FORE_COLOR": null, "FONT_FLAGS": 0, "BACK_COLOR": null }
      },
      {
        "ordinal": 150,
        "value": 1,
        "formattedValue": "1",
        "properties": { "FORE_COLOR": null, "FONT_FLAGS": 0, "BACK_COLOR": null }
      },
      {
        "ordinal": 151,
        "value": 1,
        "formattedValue": "1",
        "properties": { "FORE_COLOR": null, "FONT_FLAGS": 0, "BACK_COLOR": null }
      },
      {
        "ordinal": 156,
        "value": 0,
        "formattedValue": "0",
        "properties": { "FORE_COLOR": null, "FONT_FLAGS": 0, "BACK_COLOR": null }
      },
      {
        "ordinal": 157,
        "value": 0,
        "formattedValue": "0",
        "properties": { "FORE_COLOR": null, "FONT_FLAGS": 0, "BACK_COLOR": null }
      },
      {
        "ordinal": 162,
        "value": 0,
        "formattedValue": "0",
        "properties": { "FORE_COLOR": null, "FONT_FLAGS": 0, "BACK_COLOR": null }
      },
      {
        "ordinal": 163,
        "value": 0,
        "formattedValue": "0",
        "properties": { "FORE_COLOR": null, "FONT_FLAGS": 0, "BACK_COLOR": null }
      },
      {
        "ordinal": 168,
        "value": 0,
        "formattedValue": "0",
        "properties": { "FORE_COLOR": null, "FONT_FLAGS": 0, "BACK_COLOR": null }
      },
      {
        "ordinal": 169,
        "value": 0,
        "formattedValue": "0",
        "properties": { "FORE_COLOR": null, "FONT_FLAGS": 0, "BACK_COLOR": null }
      },
      {
        "ordinal": 174,
        "value": 1,
        "formattedValue": "1",
        "properties": { "FORE_COLOR": null, "FONT_FLAGS": 0, "BACK_COLOR": null }
      },
      {
        "ordinal": 175,
        "value": 1,
        "formattedValue": "1",
        "properties": { "FORE_COLOR": null, "FONT_FLAGS": 0, "BACK_COLOR": null }
      },
      {
        "ordinal": 180,
        "value": 3,
        "formattedValue": "3",
        "properties": { "FORE_COLOR": null, "FONT_FLAGS": 0, "BACK_COLOR": null }
      },
      {
        "ordinal": 182,
        "value": 3,
        "formattedValue": "3",
        "properties": { "FORE_COLOR": null, "FONT_FLAGS": 0, "BACK_COLOR": null }
      },
      {
        "ordinal": 186,
        "value": 0,
        "formattedValue": "0",
        "properties": { "FORE_COLOR": null, "FONT_FLAGS": 0, "BACK_COLOR": null }
      },
      {
        "ordinal": 187,
        "value": 0,
        "formattedValue": "0",
        "properties": { "FORE_COLOR": null, "FONT_FLAGS": 0, "BACK_COLOR": null }
      },
      {
        "ordinal": 192,
        "value": 6,
        "formattedValue": "6",
        "properties": { "FORE_COLOR": null, "FONT_FLAGS": 0, "BACK_COLOR": null }
      },
      {
        "ordinal": 196,
        "value": 6,
        "formattedValue": "6",
        "properties": { "FORE_COLOR": null, "FONT_FLAGS": 0, "BACK_COLOR": null }
      },
      {
        "ordinal": 198,
        "value": 1,
        "formattedValue": "1",
        "properties": { "FORE_COLOR": null, "FONT_FLAGS": 0, "BACK_COLOR": null }
      },
      {
        "ordinal": 200,
        "value": 1,
        "formattedValue": "1",
        "properties": { "FORE_COLOR": null, "FONT_FLAGS": 0, "BACK_COLOR": null }
      },
      {
        "ordinal": 204,
        "value": 5,
        "formattedValue": "5",
        "properties": { "FORE_COLOR": null, "FONT_FLAGS": 0, "BACK_COLOR": null }
      },
      {
        "ordinal": 209,
        "value": 5,
        "formattedValue": "5",
        "properties": { "FORE_COLOR": null, "FONT_FLAGS": 0, "BACK_COLOR": null }
      },
      {
        "ordinal": 210,
        "value": 4,
        "formattedValue": "4",
        "properties": { "FORE_COLOR": null, "FONT_FLAGS": 0, "BACK_COLOR": null }
      },
      {
        "ordinal": 214,
        "value": 4,
        "formattedValue": "4",
        "properties": { "FORE_COLOR": null, "FONT_FLAGS": 0, "BACK_COLOR": null }
      },
      {
        "ordinal": 216,
        "value": 0,
        "formattedValue": "0",
        "properties": { "FORE_COLOR": null, "FONT_FLAGS": 0, "BACK_COLOR": null }
      },
      {
        "ordinal": 217,
        "value": 0,
        "formattedValue": "0",
        "properties": { "FORE_COLOR": null, "FONT_FLAGS": 0, "BACK_COLOR": null }
      },
      {
        "ordinal": 222,
        "value": 0,
        "formattedValue": "0",
        "properties": { "FORE_COLOR": null, "FONT_FLAGS": 0, "BACK_COLOR": null }
      },
      {
        "ordinal": 223,
        "value": 0,
        "formattedValue": "0",
        "properties": { "FORE_COLOR": null, "FONT_FLAGS": 0, "BACK_COLOR": null }
      },
      {
        "ordinal": 228,
        "value": 0,
        "formattedValue": "0",
        "properties": { "FORE_COLOR": null, "FONT_FLAGS": 0, "BACK_COLOR": null }
      },
      {
        "ordinal": 229,
        "value": 0,
        "formattedValue": "0",
        "properties": { "FORE_COLOR": null, "FONT_FLAGS": 0, "BACK_COLOR": null }
      },
      {
        "ordinal": 234,
        "value": 0,
        "formattedValue": "0",
        "properties": { "FORE_COLOR": null, "FONT_FLAGS": 0, "BACK_COLOR": null }
      },
      {
        "ordinal": 235,
        "value": 0,
        "formattedValue": "0",
        "properties": { "FORE_COLOR": null, "FONT_FLAGS": 0, "BACK_COLOR": null }
      },
      {
        "ordinal": 240,
        "value": 0,
        "formattedValue": "0",
        "properties": { "FORE_COLOR": null, "FONT_FLAGS": 0, "BACK_COLOR": null }
      },
      {
        "ordinal": 241,
        "value": 0,
        "formattedValue": "0",
        "properties": { "FORE_COLOR": null, "FONT_FLAGS": 0, "BACK_COLOR": null }
      },
      {
        "ordinal": 246,
        "value": 0,
        "formattedValue": "0",
        "properties": { "FORE_COLOR": null, "FONT_FLAGS": 0, "BACK_COLOR": null }
      },
      {
        "ordinal": 247,
        "value": 0,
        "formattedValue": "0",
        "properties": { "FORE_COLOR": null, "FONT_FLAGS": 0, "BACK_COLOR": null }
      },
      {
        "ordinal": 252,
        "value": 0,
        "formattedValue": "0",
        "properties": { "FORE_COLOR": null, "FONT_FLAGS": 0, "BACK_COLOR": null }
      },
      {
        "ordinal": 253,
        "value": 0,
        "formattedValue": "0",
        "properties": { "FORE_COLOR": null, "FONT_FLAGS": 0, "BACK_COLOR": null }
      },
      {
        "ordinal": 258,
        "value": 1,
        "formattedValue": "1",
        "properties": { "FORE_COLOR": null, "FONT_FLAGS": 0, "BACK_COLOR": null }
      },
      {
        "ordinal": 260,
        "value": 1,
        "formattedValue": "1",
        "properties": { "FORE_COLOR": null, "FONT_FLAGS": 0, "BACK_COLOR": null }
      },
      {
        "ordinal": 264,
        "value": 0,
        "formattedValue": "0",
        "properties": { "FORE_COLOR": null, "FONT_FLAGS": 0, "BACK_COLOR": null }
      },
      {
        "ordinal": 265,
        "value": 0,
        "formattedValue": "0",
        "properties": { "FORE_COLOR": null, "FONT_FLAGS": 0, "BACK_COLOR": null }
      },
      {
        "ordinal": 270,
        "value": 3,
        "formattedValue": "3",
        "properties": { "FORE_COLOR": null, "FONT_FLAGS": 0, "BACK_COLOR": null }
      },
      {
        "ordinal": 272,
        "value": 3,
        "formattedValue": "3",
        "properties": { "FORE_COLOR": null, "FONT_FLAGS": 0, "BACK_COLOR": null }
      },
      {
        "ordinal": 276,
        "value": 0,
        "formattedValue": "0",
        "properties": { "FORE_COLOR": null, "FONT_FLAGS": 0, "BACK_COLOR": null }
      },
      {
        "ordinal": 277,
        "value": 0,
        "formattedValue": "0",
        "properties": { "FORE_COLOR": null, "FONT_FLAGS": 0, "BACK_COLOR": null }
      },
      {
        "ordinal": 282,
        "value": 0,
        "formattedValue": "0",
        "properties": { "FORE_COLOR": null, "FONT_FLAGS": 0, "BACK_COLOR": null }
      },
      {
        "ordinal": 283,
        "value": 0,
        "formattedValue": "0",
        "properties": { "FORE_COLOR": null, "FONT_FLAGS": 0, "BACK_COLOR": null }
      }
    ],
    "defaultMembers": [
      {
        "dimension": "Measures",
        "hierarchy": "Measures",
        "path": ["contributors.COUNT"],
        "captionPath": ["contributors.COUNT"]
      }
    ]
  }
}
